idyntree/__init__.py
idyntree/_iDynTree.so
idyntree/bindings.py
idyntree/swig.py
idyntree/bin/__main__.py
idyntree/bin/idyntree-model-info
idyntree/bin/idyntree-model-view-meshcat
idyntree/include/iDynTree/AccelerometerSensor.h
idyntree/include/iDynTree/AllSensorsTypes.h
idyntree/include/iDynTree/ArticulatedBodyInertia.h
idyntree/include/iDynTree/AttitudeEstimator.h
idyntree/include/iDynTree/AttitudeMahonyFilter.h
idyntree/include/iDynTree/AttitudeQuaternionEKF.h
idyntree/include/iDynTree/Axis.h
idyntree/include/iDynTree/BerdyHelper.h
idyntree/include/iDynTree/BerdySparseMAPSolver.h
idyntree/include/iDynTree/BipedFootContactClassifier.h
idyntree/include/iDynTree/BoundingBoxHelpers.h
idyntree/include/iDynTree/ClassicalAcc.h
idyntree/include/iDynTree/Constraint.h
idyntree/include/iDynTree/ConstraintsGroup.h
idyntree/include/iDynTree/ContactStateMachine.h
idyntree/include/iDynTree/ContactWrench.h
idyntree/include/iDynTree/ControlledDynamicalSystem.h
idyntree/include/iDynTree/Controller.h
idyntree/include/iDynTree/ConvexHullHelpers.h
idyntree/include/iDynTree/CoreExport.h
idyntree/include/iDynTree/Cost.h
idyntree/include/iDynTree/CubicSpline.h
idyntree/include/iDynTree/DenavitHartenberg.h
idyntree/include/iDynTree/Direction.h
idyntree/include/iDynTree/DynamicalSystem.h
idyntree/include/iDynTree/Dynamics.h
idyntree/include/iDynTree/DynamicsLinearization.h
idyntree/include/iDynTree/DynamicsLinearizationHelpers.h
idyntree/include/iDynTree/EigenHelpers.h
idyntree/include/iDynTree/EigenMathHelpers.h
idyntree/include/iDynTree/EigenSparseHelpers.h
idyntree/include/iDynTree/ExtWrenchesAndJointTorquesEstimator.h
idyntree/include/iDynTree/ExtendedKalmanFilter.h
idyntree/include/iDynTree/ExternalWrenchesEstimation.h
idyntree/include/iDynTree/FixedJoint.h
idyntree/include/iDynTree/ForwardKinematics.h
idyntree/include/iDynTree/FreeFloatingMatrices.h
idyntree/include/iDynTree/FreeFloatingState.h
idyntree/include/iDynTree/GeomVector3.h
idyntree-14.2.0.dist-info/METADATA
idyntree-14.2.0.dist-info/WHEEL
idyntree-14.2.0.dist-info/entry_points.txt
idyntree-14.2.0.dist-info/top_level.txt
idyntree-14.2.0.dist-info/RECORD
idyntree-14.2.0.dist-info/licenses/LICENSE
