Metadata-Version: 2.4
Name: idyntree
Version: 14.2.0
Summary: Multibody Dynamics Library designed for Free Floating Robots.
Home-page: https://github.com/robotology/idyntree
Author: Diego Ferigo
Author-email: dgferigo@gmail.com
License: BSD-3-Clause
Project-URL: Tracker, https://github.com/robotology/idyntree/issues
Project-URL: Documentation, https://robotology.github.io/idyntree/master/
Project-URL: Source, https://github.com/robotology/idyntree
Keywords: robotics,dynamics,free-floating,floating-base,robot,robotic-library,multibody-dynamics
Platform: any
Classifier: Development Status :: 5 - Production/Stable
Classifier: Operating System :: POSIX :: Linux
Classifier: Operating System :: MacOS
Classifier: Operating System :: Microsoft :: Windows
Classifier: Framework :: Robot Framework
Classifier: Intended Audience :: Education
Classifier: Intended Audience :: Developers
Classifier: Intended Audience :: Science/Research
Classifier: Programming Language :: C++
Classifier: Programming Language :: Python :: 3.6
Classifier: Programming Language :: Python :: 3.7
Classifier: Programming Language :: Python :: 3.8
Classifier: Programming Language :: Python :: 3.9
Classifier: Programming Language :: Python :: 3 :: Only
Classifier: Programming Language :: Python :: Implementation :: CPython
Classifier: License :: OSI Approved :: BSD License
Requires-Python: >=3.6
License-File: LICENSE
Requires-Dist: numpy
Dynamic: license-file
